{"_type":"export","__export_format":4,"__export_date":"2020-10-24T14:23:22.282Z","__export_source":"insomnia.desktop.app:v2020.4.1","resources":[{"_id":"req_46091c9dafd943998cc00f234c879214","parentId":"fld_feb7e1efa90b43b89eb81b8e5faa6d06","modified":1603549188680,"created":1603547259125,"url":"{{ faq }}/add","name":"Insert Faq","description":"","method":"POST","body":{"mimeType":"application/x-www-form-urlencoded","params":[]},"parameters":[{"name":"datahora","value":"2020-10-24 11:38:59","description":"","id":"pair_c16aa070982542c7ad1a37cb071742cd"},{"name":"texto","value":"Produto bom","description":"","id":"pair_381a86e6f1d24789acf2d374fcd27d0e"},{"name":"id_produto","value":"2","description":"","id":"pair_216d36bea048415abfd873a5c4dce50b"}],"headers":[{"name":"Content-Type","value":"application/x-www-form-urlencoded","id":"pair_05999f8167a445ebaf0ddc797ed1179e"}],"authentication":{},"metaSortKey":-1603416734210.375,"isPrivate":false,"settingStoreCookies":true,"settingSendCookies":true,"settingDisableRenderRequestBody":false,"settingEncodeUrl":true,"settingRebuildPath":true,"settingFollowRedirects":"global","_type":"request"},{"_id":"fld_feb7e1efa90b43b89eb81b8e5faa6d06","parentId":"fld_3c3e73951f224b9aafb8173d0f27a055","modified":1603547242003,"created":1603547242003,"name":"FaqController","description":"","environment":{},"environmentPropertyOrder":null,"metaSortKey":-1603547242003,"_type":"request_group"},{"_id":"fld_3c3e73951f224b9aafb8173d0f27a055","parentId":"wrk_bac26fc12fbd4471a52cd17167c8666f","modified":1603408890104,"created":1603408890104,"name":"LojaUnit","description":"","environment":{},"environmentPropertyOrder":null,"metaSortKey":-1603408890105,"_type":"request_group"},{"_id":"wrk_bac26fc12fbd4471a52cd17167c8666f","parentId":null,"modified":1590968663704,"created":1590968663704,"name":"Insomnia","description":"","scope":null,"_type":"workspace"},{"_id":"req_e0655c3dd2384d8c87c78db22e530011","parentId":"fld_feb7e1efa90b43b89eb81b8e5faa6d06","modified":1603549178125,"created":1603547253494,"url":"{{ faq }}/all","name":"All Faq","description":"","method":"GET","body":{},"parameters":[],"headers":[],"authentication":{},"metaSortKey":-1603416734160.375,"isPrivate":false,"settingStoreCookies":true,"settingSendCookies":true,"settingDisableRenderRequestBody":false,"settingEncodeUrl":true,"settingRebuildPath":true,"settingFollowRedirects":"global","_type":"request"},{"_id":"req_ba46b8038ca54f88bbe6a3f93a63ac5e","parentId":"fld_feb7e1efa90b43b89eb81b8e5faa6d06","modified":1603549295427,"created":1603548278494,"url":"{{ faq }}/find/3","name":"Find By ID","description":"","method":"GET","body":{},"parameters":[],"headers":[],"authentication":{},"metaSortKey":-1603416734110.375,"isPrivate":false,"settingStoreCookies":true,"settingSendCookies":true,"settingDisableRenderRequestBody":false,"settingEncodeUrl":true,"settingRebuildPath":true,"settingFollowRedirects":"global","_type":"request"},{"_id":"req_6503eec6480947a89f7c35807d85053b","parentId":"fld_3595291a775d439a8251b827c90a866a","modified":1603546382859,"created":1603416709983,"url":"{{ clientes }}/delete/all","name":"Delete All","description":"","method":"DELETE","body":{},"parameters":[],"headers":[],"authentication":{},"metaSortKey":-1603416734201,"isPrivate":false,"settingStoreCookies":true,"settingSendCookies":true,"settingDisableRenderRequestBody":false,"settingEncodeUrl":true,"settingRebuildPath":true,"settingFollowRedirects":"global","_type":"request"},{"_id":"fld_3595291a775d439a8251b827c90a866a","parentId":"fld_3c3e73951f224b9aafb8173d0f27a055","modified":1603494922727,"created":1603494922727,"name":"ClienteController","description":"","environment":{},"environmentPropertyOrder":null,"metaSortKey":-1603494922727,"_type":"request_group"},{"_id":"req_92b4ca3bd4fa433d9a25bb1216705c23","parentId":"fld_3595291a775d439a8251b827c90a866a","modified":1603546400915,"created":1603416695500,"url":"{{ clientes }}/find/1","name":"Find By ID","description":"","method":"GET","body":{},"parameters":[],"headers":[],"authentication":{},"metaSortKey":-1603416734176,"isPrivate":false,"settingStoreCookies":true,"settingSendCookies":true,"settingDisableRenderRequestBody":false,"settingEncodeUrl":true,"settingRebuildPath":true,"settingFollowRedirects":"global","_type":"request"},{"_id":"req_1771b51238d1407e998172cfdb11f420","parentId":"fld_3595291a775d439a8251b827c90a866a","modified":1603546453939,"created":1603408923078,"url":"{{ clientes }}/all","name":"All Clientes","description":"","method":"GET","body":{},"parameters":[],"headers":[],"authentication":{},"metaSortKey":-1603416734163.5,"isPrivate":false,"settingStoreCookies":true,"settingSendCookies":true,"settingDisableRenderRequestBody":false,"settingEncodeUrl":true,"settingRebuildPath":true,"settingFollowRedirects":"global","_type":"request"},{"_id":"req_f8e2960e85f640b7a123512ae8beb534","parentId":"fld_3595291a775d439a8251b827c90a866a","modified":1603546652782,"created":1603409009381,"url":"{{ clientes }}/add","name":"Insert Cliente","description":"","method":"POST","body":{"mimeType":"application/x-www-form-urlencoded","params":[{"name":"nome","value":"Daad","description":"","id":"pair_e021ba3b5fa844d6ba10a29da3158fb2"},{"name":"cpf","value":"99966633355","description":"","id":"pair_7f9aeb0934ec4c7fadfbcde89e53f9b7"},{"name":"email","value":"Daad@email","description":"","id":"pair_f5a84b2d035743c3b9bad691e942c249"},{"name":"dataNascimento","value":"1970-10-15","description":"","id":"pair_c61c47b5ba7b4456a45474efbc876f0e"},{"name":"sexo","value":"F","description":"","id":"pair_f039165dfad642949707164a93337dfa"},{"name":"nomeSocial","value":"Dd","description":"","id":"pair_11594f6d48df4c83aa659ac1514f8aca"},{"name":"apelido","value":"Dad","description":"","id":"pair_ad91d3b4f2264880976f2167d6c0a79b"},{"name":"telefone","value":"912312456","description":"","id":"pair_5a9ca371a7fd4d3d912e03623ba43b46"}]},"parameters":[],"headers":[{"name":"Content-Type","value":"application/x-www-form-urlencoded","id":"pair_05999f8167a445ebaf0ddc797ed1179e"}],"authentication":{},"metaSortKey":-1603416734157.25,"isPrivate":false,"settingStoreCookies":true,"settingSendCookies":true,"settingDisableRenderRequestBody":false,"settingEncodeUrl":true,"settingRebuildPath":true,"settingFollowRedirects":"global","_type":"request"},{"_id":"req_ed1a8cd83ac943508d52570786c07064","parentId":"fld_3595291a775d439a8251b827c90a866a","modified":1603546496434,"created":1603416734151,"url":"{{ clientes }}/delete/1","name":"Delete By ID","description":"","method":"DELETE","body":{},"parameters":[],"headers":[],"authentication":{},"metaSortKey":-1603416734151,"isPrivate":false,"settingStoreCookies":true,"settingSendCookies":true,"settingDisableRenderRequestBody":false,"settingEncodeUrl":true,"settingRebuildPath":true,"settingFollowRedirects":"global","_type":"request"},{"_id":"req_1173163770a84b87a9c3a79bd9b11ea0","parentId":"fld_1254688469124db9b1a22a72d901c734","modified":1603547114599,"created":1603493145703,"url":"{{ fornecedor }}/add","name":"Insert Fornecedor","description":"","method":"POST","body":{"mimeType":"application/x-www-form-urlencoded","params":[{"name":"nome","value":"Portaria Segurança","description":"","id":"pair_6499c32fea804d7d81c34394050d3328"},{"name":"endereco","value":"Rua do Sol 15, Ponta N., Natal/RN","description":"","id":"pair_5066b7e1aca0401a96a7c4351f0ca98f"},{"name":"telefone","value":"84 3333-2222","description":"","id":"pair_39fac3ed98b242aa8d215b6a58582fd2"},{"name":"cnpj","value":"11222333000145","description":"","id":"pair_1a2ebd0fb5d8466383a3152320af3ec9"},{"name":"email","value":"portaria@email","description":"","id":"pair_0893b73b852d43b3b8e7dff1e2ea795d"}]},"parameters":[],"headers":[{"name":"Content-Type","value":"application/x-www-form-urlencoded","id":"pair_05999f8167a445ebaf0ddc797ed1179e"}],"authentication":{},"metaSortKey":-1603324643871,"isPrivate":false,"settingStoreCookies":true,"settingSendCookies":true,"settingDisableRenderRequestBody":false,"settingEncodeUrl":true,"settingRebuildPath":true,"settingFollowRedirects":"global","_type":"request"},{"_id":"fld_1254688469124db9b1a22a72d901c734","parentId":"fld_3c3e73951f224b9aafb8173d0f27a055","modified":1603494975039,"created":1603493087136,"name":"FornecedorController","description":"","environment":{},"environmentPropertyOrder":null,"metaSortKey":-1603493997639.5,"_type":"request_group"},{"_id":"req_e16d76b3ba8d436bbc7fbff8ad330e0f","parentId":"fld_1254688469124db9b1a22a72d901c734","modified":1603547163488,"created":1603494680636,"url":"{{ fornecedor }}/delete/all","name":"Delete All","description":"","method":"DELETE","body":{},"parameters":[],"headers":[],"authentication":{},"metaSortKey":-1603324643864.75,"isPrivate":false,"settingStoreCookies":true,"settingSendCookies":true,"settingDisableRenderRequestBody":false,"settingEncodeUrl":true,"settingRebuildPath":true,"settingFollowRedirects":"global","_type":"request"},{"_id":"req_ddf728e0c525478cab5f4b828d2bfc6c","parentId":"fld_1254688469124db9b1a22a72d901c734","modified":1603547289936,"created":1603494674276,"url":"{{ fornecedor }}/delete/4","name":"Delete By ID","description":"","method":"DELETE","body":{},"parameters":[],"headers":[],"authentication":{},"metaSortKey":-1603324643858.5,"isPrivate":false,"settingStoreCookies":true,"settingSendCookies":true,"settingDisableRenderRequestBody":false,"settingEncodeUrl":true,"settingRebuildPath":true,"settingFollowRedirects":"global","_type":"request"},{"_id":"req_eea9e352c62040d8a6baad8d95cb143f","parentId":"fld_1254688469124db9b1a22a72d901c734","modified":1603547327073,"created":1603493873844,"url":"{{ fornecedor }}/find/2","name":"Find By ID","description":"","method":"GET","body":{},"parameters":[],"headers":[],"authentication":{},"metaSortKey":-1603324643846,"isPrivate":false,"settingStoreCookies":true,"settingSendCookies":true,"settingDisableRenderRequestBody":false,"settingEncodeUrl":true,"settingRebuildPath":true,"settingFollowRedirects":"global","_type":"request"},{"_id":"req_3c92f4ecea9f44f580335a558e32a2a6","parentId":"fld_1254688469124db9b1a22a72d901c734","modified":1603547337954,"created":1603493103977,"url":"{{ fornecedor }}/all","name":"All Fornecedor","description":"","method":"GET","body":{},"parameters":[],"headers":[],"authentication":{},"metaSortKey":-1603324643821,"isPrivate":false,"settingStoreCookies":true,"settingSendCookies":true,"settingDisableRenderRequestBody":false,"settingEncodeUrl":true,"settingRebuildPath":true,"settingFollowRedirects":"global","_type":"request"},{"_id":"req_1fe70c249a0b4ba9ad2d05bb8df60b15","parentId":"fld_bc8dc4873bea4815b22c264ffdd2e86d","modified":1603547392231,"created":1603495005711,"url":"{{ marca }}/all","name":"All Marca","description":"","method":"GET","body":{},"parameters":[],"headers":[],"authentication":{},"metaSortKey":-1603493997577,"isPrivate":false,"settingStoreCookies":true,"settingSendCookies":true,"settingDisableRenderRequestBody":false,"settingEncodeUrl":true,"settingRebuildPath":true,"settingFollowRedirects":"global","_type":"request"},{"_id":"fld_bc8dc4873bea4815b22c264ffdd2e86d","parentId":"fld_3c3e73951f224b9aafb8173d0f27a055","modified":1603494979061,"created":1603494908143,"name":"MarcaController","description":"","environment":{},"environmentPropertyOrder":null,"metaSortKey":-1603493997589.5,"_type":"request_group"},{"_id":"req_67e067333b584b748fc054af5a46a4aa","parentId":"fld_bc8dc4873bea4815b22c264ffdd2e86d","modified":1603547479437,"created":1603495622781,"url":"{{ marca }}/add","name":"Insert Marca","description":"","method":"POST","body":{"mimeType":"application/x-www-form-urlencoded","params":[{"name":"nome","value":"Rebook","description":"","id":"pair_15d66abf34e84bc099bfd5f7f4863299"},{"name":"descricao","value":"é uma empresa americana, originalmente inglesa, de equipamentos esportivos. Ela foi adquirida em 2005 pela Adidas por 3,8 bilhões de dólares","description":"","id":"pair_9991d6ed84e142aabf66d8d03567955d"}]},"parameters":[],"headers":[{"name":"Content-Type","value":"application/x-www-form-urlencoded","id":"pair_05999f8167a445ebaf0ddc797ed1179e"}],"authentication":{},"metaSortKey":-1603493997570.75,"isPrivate":false,"settingStoreCookies":true,"settingSendCookies":true,"settingDisableRenderRequestBody":false,"settingEncodeUrl":true,"settingRebuildPath":true,"settingFollowRedirects":"global","_type":"request"},{"_id":"req_77bb9c31bdc44944b719b711f1e6f748","parentId":"fld_bc8dc4873bea4815b22c264ffdd2e86d","modified":1603547956851,"created":1603495618499,"url":"{{ marca }}/delete/all","name":"Delete All","description":"","method":"DELETE","body":{},"parameters":[],"headers":[],"authentication":{},"metaSortKey":-1603493997564.5,"isPrivate":false,"settingStoreCookies":true,"settingSendCookies":true,"settingDisableRenderRequestBody":false,"settingEncodeUrl":true,"settingRebuildPath":true,"settingFollowRedirects":"global","_type":"request"},{"_id":"req_81f2272426b844b19e1b3c952b6c1441","parentId":"fld_bc8dc4873bea4815b22c264ffdd2e86d","modified":1603548108555,"created":1603495611508,"url":"{{ marca }}/delete/28","name":"Delete By ID","description":"","method":"DELETE","body":{},"parameters":[],"headers":[],"authentication":{},"metaSortKey":-1603493997552,"isPrivate":false,"settingStoreCookies":true,"settingSendCookies":true,"settingDisableRenderRequestBody":false,"settingEncodeUrl":true,"settingRebuildPath":true,"settingFollowRedirects":"global","_type":"request"},{"_id":"req_e89087334338420ea5b2231bcffd7d42","parentId":"fld_bc8dc4873bea4815b22c264ffdd2e86d","modified":1603548183975,"created":1603495603788,"url":"{{ marca }}/find/28","name":"Find By ID","description":"","method":"GET","body":{},"parameters":[],"headers":[],"authentication":{},"metaSortKey":-1603493997527,"isPrivate":false,"settingStoreCookies":true,"settingSendCookies":true,"settingDisableRenderRequestBody":false,"settingEncodeUrl":true,"settingRebuildPath":true,"settingFollowRedirects":"global","_type":"request"},{"_id":"req_d36311a91f9f4147adfc378f70fa28bb","parentId":"fld_d009e49f845f4c439f55538d2a2b2b06","modified":1603548241799,"created":1603497081921,"url":"{{ categoria }}/all","name":"All Categoria","description":"","method":"GET","body":{},"parameters":[],"headers":[],"authentication":{},"metaSortKey":-1603493997577,"isPrivate":false,"settingStoreCookies":true,"settingSendCookies":true,"settingDisableRenderRequestBody":false,"settingEncodeUrl":true,"settingRebuildPath":true,"settingFollowRedirects":"global","_type":"request"},{"_id":"fld_d009e49f845f4c439f55538d2a2b2b06","parentId":"fld_3c3e73951f224b9aafb8173d0f27a055","modified":1603497081911,"created":1603497081911,"name":"CategoriaController","description":"","environment":{},"environmentPropertyOrder":null,"metaSortKey":-1603451443847.25,"_type":"request_group"},{"_id":"req_351f14e29e484d4cbbaa61d22b8ba719","parentId":"fld_d009e49f845f4c439f55538d2a2b2b06","modified":1603548259301,"created":1603497081972,"url":"{{ categoria }}/add","name":"Insert Categoria","description":"","method":"POST","body":{"mimeType":"application/x-www-form-urlencoded","params":[]},"parameters":[{"name":"nome","value":"Utilitários","description":"","id":"pair_c16aa070982542c7ad1a37cb071742cd"},{"name":"ativo","value":"true","description":"","id":"pair_381a86e6f1d24789acf2d374fcd27d0e"}],"headers":[{"name":"Content-Type","value":"application/x-www-form-urlencoded","id":"pair_05999f8167a445ebaf0ddc797ed1179e"}],"authentication":{},"metaSortKey":-1603493997570.75,"isPrivate":false,"settingStoreCookies":true,"settingSendCookies":true,"settingDisableRenderRequestBody":false,"settingEncodeUrl":true,"settingRebuildPath":true,"settingFollowRedirects":"global","_type":"request"},{"_id":"req_a36746a758844c6594e1e749eaeac783","parentId":"fld_d009e49f845f4c439f55538d2a2b2b06","modified":1603548283854,"created":1603497081959,"url":"{{ categoria }}/delete/all","name":"Delete All","description":"","method":"DELETE","body":{},"parameters":[],"headers":[],"authentication":{},"metaSortKey":-1603493997564.5,"isPrivate":false,"settingStoreCookies":true,"settingSendCookies":true,"settingDisableRenderRequestBody":false,"settingEncodeUrl":true,"settingRebuildPath":true,"settingFollowRedirects":"global","_type":"request"},{"_id":"req_5664aa984e334f09869aa6a6d0f67080","parentId":"fld_d009e49f845f4c439f55538d2a2b2b06","modified":1603548313091,"created":1603497081941,"url":"{{ categoria }}/delete/29","name":"Delete By ID","description":"","method":"DELETE","body":{},"parameters":[],"headers":[],"authentication":{},"metaSortKey":-1603493997552,"isPrivate":false,"settingStoreCookies":true,"settingSendCookies":true,"settingDisableRenderRequestBody":false,"settingEncodeUrl":true,"settingRebuildPath":true,"settingFollowRedirects":"global","_type":"request"},{"_id":"req_640192c1837e4e8ea7395bf0027a2e5a","parentId":"fld_d009e49f845f4c439f55538d2a2b2b06","modified":1603548329302,"created":1603497081928,"url":"{{ categoria }}/find/29","name":"Find By ID","description":"","method":"GET","body":{},"parameters":[],"headers":[],"authentication":{},"metaSortKey":-1603493997527,"isPrivate":false,"settingStoreCookies":true,"settingSendCookies":true,"settingDisableRenderRequestBody":false,"settingEncodeUrl":true,"settingRebuildPath":true,"settingFollowRedirects":"global","_type":"request"},{"_id":"req_97adb17c424d495ea95e66175daddb99","parentId":"fld_db510db3f77f4840a4c1cbc466c18d44","modified":1603548378377,"created":1603497782902,"url":"{{ formapagamento }}/all","name":"All Forma de Pagamento","description":"","method":"GET","body":{},"parameters":[],"headers":[],"authentication":{},"metaSortKey":-1603493997577,"isPrivate":false,"settingStoreCookies":true,"settingSendCookies":true,"settingDisableRenderRequestBody":false,"settingEncodeUrl":true,"settingRebuildPath":true,"settingFollowRedirects":"global","_type":"request"},{"_id":"fld_db510db3f77f4840a4c1cbc466c18d44","parentId":"fld_3c3e73951f224b9aafb8173d0f27a055","modified":1603497782896,"created":1603497782896,"name":"FormaPagamentoController","description":"","environment":{},"environmentPropertyOrder":null,"metaSortKey":-1603430166976.125,"_type":"request_group"},{"_id":"req_2d541fa5dc7844e7988320d88dc39b12","parentId":"fld_db510db3f77f4840a4c1cbc466c18d44","modified":1603548395803,"created":1603497782926,"url":"{{ formapagamento }}/add","name":"Insert Forma de Pagamento","description":"","method":"POST","body":{"mimeType":"application/x-www-form-urlencoded","params":[]},"parameters":[{"name":"forma","value":"Débito","description":"","id":"pair_c16aa070982542c7ad1a37cb071742cd"},{"name":"descricao","value":"Pagamento efetuado com cartão de Débito","description":"","id":"pair_381a86e6f1d24789acf2d374fcd27d0e"},{"name":"ativo","value":"true","description":"","id":"pair_67ea6b65134a429f8a4ecd29871afa4e"}],"headers":[{"name":"Content-Type","value":"application/x-www-form-urlencoded","id":"pair_05999f8167a445ebaf0ddc797ed1179e"}],"authentication":{},"metaSortKey":-1603493997570.75,"isPrivate":false,"settingStoreCookies":true,"settingSendCookies":true,"settingDisableRenderRequestBody":false,"settingEncodeUrl":true,"settingRebuildPath":true,"settingFollowRedirects":"global","_type":"request"},{"_id":"req_9589e30ca6f0464eb1bd29f035783b0d","parentId":"fld_db510db3f77f4840a4c1cbc466c18d44","modified":1603548412969,"created":1603497782920,"url":"{{ formapagamento }}/delete/all","name":"Delete All","description":"","method":"DELETE","body":{},"parameters":[],"headers":[],"authentication":{},"metaSortKey":-1603493997564.5,"isPrivate":false,"settingStoreCookies":true,"settingSendCookies":true,"settingDisableRenderRequestBody":false,"settingEncodeUrl":true,"settingRebuildPath":true,"settingFollowRedirects":"global","_type":"request"},{"_id":"req_0e08c1cca461414bb919c7e60824b983","parentId":"fld_db510db3f77f4840a4c1cbc466c18d44","modified":1603548437121,"created":1603497782914,"url":"{{ formapagamento }}/delete/30","name":"Delete By ID","description":"","method":"DELETE","body":{},"parameters":[],"headers":[],"authentication":{},"metaSortKey":-1603493997552,"isPrivate":false,"settingStoreCookies":true,"settingSendCookies":true,"settingDisableRenderRequestBody":false,"settingEncodeUrl":true,"settingRebuildPath":true,"settingFollowRedirects":"global","_type":"request"},{"_id":"req_4b75dc0deb2f4551810b22ddaf27fed6","parentId":"fld_db510db3f77f4840a4c1cbc466c18d44","modified":1603548469303,"created":1603497782909,"url":"{{ formapagamento }}/find/23","name":"Find By ID","description":"","method":"GET","body":{},"parameters":[],"headers":[],"authentication":{},"metaSortKey":-1603493997527,"isPrivate":false,"settingStoreCookies":true,"settingSendCookies":true,"settingDisableRenderRequestBody":false,"settingEncodeUrl":true,"settingRebuildPath":true,"settingFollowRedirects":"global","_type":"request"},{"_id":"env_d8d7ab89fc9fb8e7d00affbdaecc012cd74cf73f","parentId":"wrk_bac26fc12fbd4471a52cd17167c8666f","modified":1603546327799,"created":1590968663772,"name":"Base Environment","data":{"root":"http://localhost:8080","clientes":"{{ root }}/clientes","formapagamento":"{{ root }}/formapagamento","itensvenda":"{{ root }}/itensvenda","categoria":"{{ root }}/categoria","marca":"{{ root }}/marca","fornecedor":"{{ root }}/fornecedor","produto":"{{ root }}/produto","venda":"{{ root }}/venda","faq":"{{ root }}/faq"},"dataPropertyOrder":{"&":["root","clientes","formapagamento","itensvenda","categoria","marca","fornecedor","produto","venda","faq"]},"color":null,"isPrivate":false,"metaSortKey":1590968663772,"_type":"environment"},{"_id":"jar_d8d7ab89fc9fb8e7d00affbdaecc012cd74cf73f","parentId":"wrk_bac26fc12fbd4471a52cd17167c8666f","modified":1590968663777,"created":1590968663777,"name":"Default Jar","cookies":[],"_type":"cookie_jar"},{"_id":"spc_399e2ef19e0248488c68355ea1c7da75","parentId":"wrk_bac26fc12fbd4471a52cd17167c8666f","modified":1591052730863,"created":1591052730863,"fileName":"Insomnia","contents":"","contentType":"yaml","_type":"api_spec"}]}